MANIFEST.in
README.md
meta.json
setup.py
en_prompt_nsfw_pipeline_bow/__init__.py
en_prompt_nsfw_pipeline_bow/meta.json
en_prompt_nsfw_pipeline_bow.egg-info/PKG-INFO
en_prompt_nsfw_pipeline_bow.egg-info/SOURCES.txt
en_prompt_nsfw_pipeline_bow.egg-info/dependency_links.txt
en_prompt_nsfw_pipeline_bow.egg-info/entry_points.txt
en_prompt_nsfw_pipeline_bow.egg-info/not-zip-safe
en_prompt_nsfw_pipeline_bow.egg-info/requires.txt
en_prompt_nsfw_pipeline_bow.egg-info/top_level.txt
en_prompt_nsfw_pipeline_bow/en_prompt_nsfw_pipeline_bow-0.3.0/README.md
en_prompt_nsfw_pipeline_bow/en_prompt_nsfw_pipeline_bow-0.3.0/config.cfg
en_prompt_nsfw_pipeline_bow/en_prompt_nsfw_pipeline_bow-0.3.0/meta.json
en_prompt_nsfw_pipeline_bow/en_prompt_nsfw_pipeline_bow-0.3.0/tokenizer
en_prompt_nsfw_pipeline_bow/en_prompt_nsfw_pipeline_bow-0.3.0/textcat/cfg
en_prompt_nsfw_pipeline_bow/en_prompt_nsfw_pipeline_bow-0.3.0/textcat/model
en_prompt_nsfw_pipeline_bow/en_prompt_nsfw_pipeline_bow-0.3.0/vocab/key2row
en_prompt_nsfw_pipeline_bow/en_prompt_nsfw_pipeline_bow-0.3.0/vocab/lookups.bin
en_prompt_nsfw_pipeline_bow/en_prompt_nsfw_pipeline_bow-0.3.0/vocab/strings.json
en_prompt_nsfw_pipeline_bow/en_prompt_nsfw_pipeline_bow-0.3.0/vocab/vectors
en_prompt_nsfw_pipeline_bow/en_prompt_nsfw_pipeline_bow-0.3.0/vocab/vectors.cfg