Metadata-Version: 2.1
Name: en_prompt_nsfw_pipeline_bow
Version: 0.3.0
Summary: NSFW pipeline that classifies prompt, using a bag-of-words model
Home-page: 
Author: Jiayu Liu
Author-email: jiayu@mewtant.io
License: UNLICENSED
Requires-Dist: spacy<4.0.0,>=3.0.0
